validatamodel/Field.py
validatamodel/Model.py
validatamodel/Models.py
validatamodel/VType.py
validatamodel/__init__.py
validatamodel/py.typed
validatamodel-0.0.1.dist-info/METADATA
validatamodel-0.0.1.dist-info/WHEEL
validatamodel-0.0.1.dist-info/RECORD
